xlsx_to_xml-0.1.6.dist-info/METADATA
xlsx_to_xml-0.1.6.dist-info/WHEEL
xlsx_to_xml-0.1.6.dist-info/licenses/LICENSE
xlsx_to_xml/__init__.py
xlsx_to_xml/xlsx_to_xml.cpython-311-darwin.so
xlsx_to_xml-0.1.6.dist-info/RECORD
